setup.py
cli_deform.egg-info/PKG-INFO
cli_deform.egg-info/SOURCES.txt
cli_deform.egg-info/dependency_links.txt
cli_deform.egg-info/entry_points.txt
cli_deform.egg-info/requires.txt
cli_deform.egg-info/top_level.txt
src/__init__.py
src/deform.py
src/utils.py