Metadata-Version: 1.0
Name: cli-deform
Version: 1.0.1
Summary: Command-line client for Deform.io
Home-page: https://github.com/deformio/cli-deform/
Author: Gennady Chibisov
Author-email: web-chib@ya.ru
License: MIT
Platform: UNKNOWN
